pyimg4/__init__.py
pyimg4/__main__.py
pyimg4/errors.py
pyimg4/parser.py
pyimg4/types.py
pyimg4-0.8.7.dist-info/METADATA
pyimg4-0.8.7.dist-info/WHEEL
pyimg4-0.8.7.dist-info/entry_points.txt
pyimg4-0.8.7.dist-info/licenses/LICENSE
pyimg4-0.8.7.dist-info/RECORD
