Metadata-Version: 2.4
Name: pyimg4
Version: 0.8.7
Summary: A Python library/CLI tool for parsing Apple's Image4 format.
Project-URL: Repository, https://github.com/m1stadev/PyIMG4
Project-URL: Bug Tracker, https://github.com/m1stadev/PyIMG4/issues
Author-email: m1stadev <adamhamdi31@gmail.com>
License: MIT License
License-File: LICENSE
Keywords: iboot,image4,img4,ios,jailbreak
Classifier: Development Status :: 4 - Beta
Classifier: Environment :: Console
Classifier: Intended Audience :: Developers
Classifier: Intended Audience :: Science/Research
Classifier: Programming Language :: Python :: 3.9
Classifier: Topic :: Utilities
Requires-Python: >=3.9
Requires-Dist: apple-compress>=0.2.3; sys_platform == 'darwin'
Requires-Dist: asn1>=2.7.0
Requires-Dist: click>=8.1.7
Requires-Dist: lzfse>=0.4.2; sys_platform != 'darwin'
Requires-Dist: pycryptodome>=3.18.0
Requires-Dist: pylzss==0.3.4
